spotipy_playlists2excel/cred.py
spotipy_playlists2excel/playlists.py
spotipy_playlists2excel-0.0.1.dist-info/LICENSE.txt
spotipy_playlists2excel-0.0.1.dist-info/METADATA
spotipy_playlists2excel-0.0.1.dist-info/WHEEL
spotipy_playlists2excel-0.0.1.dist-info/top_level.txt
spotipy_playlists2excel-0.0.1.dist-info/RECORD
