Metadata-Version: 2.1
Name: spotipy-playlists2excel
Version: 0.0.1
Summary: A small package that exports spotify playlists to excel xlsx format.
Author-email: Example Author <bebissig@gmail.com>
Classifier: Programming Language :: Python :: 3
Classifier: License :: OSI Approved :: MIT License
Classifier: Operating System :: OS Independent
Requires-Python: >=3.7
License-File: LICENSE.txt
